selenium_geocoder.py
selenium_geocoder-1.0.0.dist-info/METADATA
selenium_geocoder-1.0.0.dist-info/WHEEL
selenium_geocoder-1.0.0.dist-info/licenses/LICENSE
selenium_geocoder-1.0.0.dist-info/RECORD
