Metadata-Version: 2.1
Name: selenium-geocoder
Version: 1.0.0
Summary: Modularizing selenium code for getting coordinates from address of a place.
Project-URL: Homepage, https://github.com/hridayK/selenium-geocoder
Project-URL: Bug Tracker, https://github.com/hridayK/selenium-geocoder/issues
Author-email: Hriday Keswani <hridaykeswnai@gmail.com>
License-File: LICENSE
Classifier: License :: OSI Approved :: MIT License
Classifier: Operating System :: OS Independent
Classifier: Programming Language :: Python :: 3
Requires-Python: >=3.7
